nindo/__init__.py
nindo/artist.py
nindo/brand.py
nindo/channel.py
nindo/charts.py
nindo/coupon.py
nindo/milestone.py
nindo/post.py
nindo/types.py
nindo/viral.py
nindo-0.0.2.dist-info/METADATA
nindo-0.0.2.dist-info/RECORD
nindo-0.0.2.dist-info/WHEEL
nindo-0.0.2.dist-info/top_level.txt
