Metadata-Version: 2.1
Name: nindo
Version: 0.0.2
Summary: Unofficial API for https://nindo.de
Home-page: UNKNOWN
Author: Marc Hauck
Author-email: marchauck04@gmail.com
License: UNKNOWN
Platform: UNKNOWN
Classifier: Programming Language :: Python :: 3
Classifier: License :: OSI Approved :: MIT License
Classifier: Operating System :: OS Independent
Requires-Python: >=3
